{
  "project_info": {
    "project_number": "3199174357",
    "firebase_url": "https://flash-chat-b4e50.firebaseio.com",
    "project_id": "flash-chat-b4e50",
    "storage_bucket": "flash-chat-b4e50.appspot.com"
  },
  "client": [
    {
      "client_info": {
        "mobilesdk_app_id": "1:3199174357:android:10158a31f16d30f827845c",
        "android_client_info": {
          "package_name": "com.carlosdoki.flash_chat_flutter"
        }
      },
      "oauth_client": [
        {
          "client_id": "3199174357-lhsdatiu535sbm2cetebjdlvvhq9lhrc.apps.googleusercontent.com",
          "client_type": 3
        }
      ],
      "api_key": [
        {
          "current_key": "AIzaSyDfrtERl96nCru80fmivloKDexo6whKFmw"
        }
      ],
      "services": {
        "appinvite_service": {
          "other_platform_oauth_client": [
            {
              "client_id": "3199174357-lhsdatiu535sbm2cetebjdlvvhq9lhrc.apps.googleusercontent.com",
              "client_type": 3
            }
          ]
        }
      }
    }
  ],
  "configuration_version": "1"
}